httpx_metrics/__init__.py
httpx_metrics/async_metrics.py
httpx_metrics/metrics_registry.py
httpx_metrics/sync_metrics.py
httpx_metrics/transport.py
httpx_metrics/_async/metrics/__init__.py
httpx_metrics/_async/metrics/base.py
httpx_metrics/_async/metrics/cached_requests.py
httpx_metrics/_async/metrics/download_duration.py
httpx_metrics/_async/metrics/processing_requests.py
httpx_metrics/_async/metrics/requests_duration.py
httpx_metrics/_async/metrics/total_requests.py
httpx_metrics/_sync/metrics/__init__.py
httpx_metrics/_sync/metrics/base.py
httpx_metrics/_sync/metrics/cached_requests.py
httpx_metrics/_sync/metrics/download_duration.py
httpx_metrics/_sync/metrics/processing_requests.py
httpx_metrics/_sync/metrics/requests_duration.py
httpx_metrics/_sync/metrics/total_requests.py
httpx_metrics-0.0.1.dist-info/METADATA
httpx_metrics-0.0.1.dist-info/WHEEL
httpx_metrics-0.0.1.dist-info/licenses/LICENSE.txt
httpx_metrics-0.0.1.dist-info/RECORD
