Metadata-Version: 2.3
Name: httpx-metrics
Version: 0.0.1
Project-URL: Issues, https://github.com/Karen Petrosyan/httpx-metrics/issues
Project-URL: Source, https://github.com/Karen Petrosyan/httpx-metrics
Author-email: Karen Petrosyan <kar.petrosyanpy@gmail.com>
License-Expression: MIT
License-File: LICENSE.txt
Classifier: Development Status :: 4 - Beta
Classifier: Programming Language :: Python
Classifier: Programming Language :: Python :: 3.8
Classifier: Programming Language :: Python :: 3.9
Classifier: Programming Language :: Python :: 3.10
Classifier: Programming Language :: Python :: 3.11
Classifier: Programming Language :: Python :: 3.12
Classifier: Programming Language :: Python :: Implementation :: CPython
Classifier: Programming Language :: Python :: Implementation :: PyPy
Requires-Python: >=3.8
Requires-Dist: prometheus-client
Provides-Extra: hishel
Requires-Dist: hishel<0.1,>=0.0.29; extra == 'hishel'
